README.rst
setup.py
alfpy/__init__.py
alfpy/bbc.py
alfpy/fcgr.py
alfpy/graphdna.py
alfpy/lempelziv.py
alfpy/ncd.py
alfpy/version.py
alfpy/wmetric.py
alfpy/word_bool_distance.py
alfpy/word_d2.py
alfpy/word_distance.py
alfpy/word_pattern.py
alfpy/word_rtd.py
alfpy/word_sets_distance.py
alfpy/word_vector.py
alfpy.egg-info/PKG-INFO
alfpy.egg-info/SOURCES.txt
alfpy.egg-info/dependency_links.txt
alfpy.egg-info/requires.txt
alfpy.egg-info/top_level.txt
alfpy/utils/__init__.py
alfpy/utils/distance.py
alfpy/utils/distmatrix.py
alfpy/utils/fasta.py
alfpy/utils/seqrecords.py
alfpy/utils/data/__init__.py
alfpy/utils/data/seqcontent.py
alfpy/utils/data/subsmat.py
bin/calc_bbc.py
bin/calc_fcgr.py
bin/calc_graphdna.py
bin/calc_lempelziv.py
bin/calc_ncd.py
bin/calc_wmetric.py
bin/calc_word.py
bin/calc_word_bool.py
bin/calc_word_cv.py
bin/calc_word_d2.py
bin/calc_word_ffp.py
bin/calc_word_rtd.py
bin/calc_word_sets.py
bin/create_wordpattern.py