Metadata-Version: 1.1
Name: alfpy
Version: 1.0.6
Summary: Alignment-free package to compare DNA/RNA/protein sequences (bioinformatics).
Home-page: http://www.combio.pl/alfree
Author: Andrzej Zielezinski
Author-email: andrzejz@amu.edu.pl
License: MIT
Keywords: alignment-free bioinformatics sequence DNA protein homology phylogeny
Platform: UNKNOWN
Classifier: License :: OSI Approved :: MIT License
Classifier: Environment :: Console
Classifier: Operating System :: MacOS
Classifier: Operating System :: POSIX :: Linux
Classifier: Programming Language :: Python :: 2
Classifier: Programming Language :: Python :: 2.7
Classifier: Programming Language :: Python :: 3
Classifier: Programming Language :: Python :: 3.3
Classifier: Programming Language :: Python :: 3.4
Classifier: Programming Language :: Python :: 3.5
Classifier: Topic :: Scientific/Engineering
Classifier: Topic :: Scientific/Engineering :: Bio-Informatics
